<model id="editor.editorModel.tp_report_revise" description="" type="TABLE" name="tp_report_revise" title="tp_report_revise">
  <groupId>groupId</groupId>
  <datasourceId>default</datasourceId>
  <incremental>false</incremental>
  <synchronous>false</synchronous>
  <removeFake>false</removeFake>
  <indexs/>
  <columns>
    <column name="id" title="id" type="3" typeTitle="高精度数值" length="20" precision="0" notNull="true" primaryKey="true" foreignKey="false" sequenceName="__PWP3_SEQ"/>
    <column name="content" title="content" type="12" typeTitle="可变长字符串" length="4000" precision="0" notNull="false" primaryKey="false" foreignKey="false"/>
    <column name="content_ctime" title="content_ctime" type="93" typeTitle="时间戳" length="7" precision="0" notNull="false" primaryKey="false" foreignKey="false"/>
    <column name="status" title="status" type="3" typeTitle="高精度数值" length="1" precision="0" notNull="false" primaryKey="false" foreignKey="false"/>
    <column name="create_time" title="create_time" type="93" typeTitle="时间戳" length="7" precision="0" notNull="false" primaryKey="false" foreignKey="false"/>
    <column name="report_id" title="report_id" type="3" typeTitle="高精度数值" length="20" precision="0" notNull="true" primaryKey="false" foreignKey="false"/>
    <column name="user_id" title="user_id" type="3" typeTitle="高精度数值" length="20" precision="0" notNull="true" primaryKey="false" foreignKey="false"/>
    <column name="content_type" title="content_type" type="3" typeTitle="高精度数值" length="1" precision="0" notNull="false" primaryKey="false" foreignKey="false"/>
  </columns>
  <primaryKeys>
    <column name="id" title="id" type="3" typeTitle="高精度数值" length="20" precision="0" notNull="true" primaryKey="true" foreignKey="false" sequenceName="__PWP3_SEQ"/>
  </primaryKeys>
  <relationships/>
  <cascadeModelRelation/>
</model>